{"jsonrpc": "2.0", "result": {"structuredContent": {"addr": "0x181b04820", "error": null, "name": "sub_181B04820", "prototype": null, "size": 8662, "decompiled": "// Hidden C++ exception states: #wind=40\n__int64 __fastcall sub_181B04820(__int64 a1, unsigned int a2)\n{\n  __int64 result; // rax\n  _OWORD *v3; // rsi\n  __int64 v4; // rcx\n  __int64 v6; // rcx\n  __int64 v7; // rax\n  __int64 v8; // rsi\n  __int64 v9; // r8\n  __int128 *v10; // rdi\n  __int64 v11; // rsi\n  bool v12; // cf\n  __int64 v13; // rdx\n  __int64 v14; // rbx\n  __int64 v15; // rax\n  __int64 v16; // rcx\n  unsigned __int64 v17; // rax\n  __int64 v18; // rcx\n  __int64 v19; // rax\n  _OWORD *v20; // rsi\n  __int128 v21; // kr00_16\n  _OWORD *v22; // rcx\n  char *v23; // rdi\n  __int64 v24; // r12\n  __int128 v25; // xmm0\n  __int64 v26; // rcx\n  __int64 v27; // rax\n  __int64 v28; // r8\n  __int64 v29; // r13\n  volatile signed __int32 *v30; // rsi\n  __int64 v31; // rdi\n  volatile signed __int32 *v32; // rax\n  volatile signed __int32 *v33; // rbx\n  int i; // r14d\n  __int128 v35; // xmm0\n  _QWORD *v36; // r15\n  __int64 v37; // rax\n  __int64 v38; // rax\n  __int64 v39; // rcx\n  volatile signed __int32 ... [2316 chars total]", "decompile_truncated": 1477, "assembly": "sub_181B04820 (.text @ 0x181b04820):\n181b04820  push rbp\n181b04821  push r15\n181b04823  push r14\n181b04825  push r13\n181b04827  push r12\n181b04829  push rsi\n181b0482a  push rdi\n181b0482b  push rbx\n181b0482c  sub rsp, 458h\n181b04833  lea rbp, [rsp+80h]\n181b0483b  movaps [rbp+410h+var_50], xmm7\n181b04842  movaps [rbp+410h+var_60], xmm6\n181b04849  mov [rbp+410h+var_68], 0FFFFFFFFFFFFFFFEh\n181b04854  cmp byte ptr [rcx+32Ch], 1\n181b0485b  jnz loc_181B04981\n181b04861  mov ecx, 4\n181b04866  call sub_180068740\n181b0486b  test eax, eax\n181b0486d  jz loc_181B0689C\n181b04873  lea rsi, [rbp+410h+var_220]\n181b0487a  mov rcx, rsi\n181b0487d  call sub_180068870\n181b04882  cmp [rbp+410h+var_208], 10h\n181b0488a  jb loc_181B04893\n181b0488c  mov rsi, qword ptr [rbp+410h+var_220]\n181b04893  lea rax, unk_1885988D3\n181b0489a  mov [rsp+490h+var_470], rax\n181b0489f  mov [rsp+490h+var_458], 0\n181b048a8  mov byte ptr [rsp+490h+var_460], 0\n181b048ad  mov dword ptr [rsp+490h+var_468], 3ADh\n181b048b5  lea r9, unk_1... [58591 chars total]", "strings": ["sendmsg_", "ZYXWVUTSRQPONMLKJIHGFEDCBA9876543210123456789ABCDEFGHIJKLMNOPQRSTUVWXYZ"], "constants": [], "callees": ["sub_1839C7B00", "sub_180CE5990", "sub_180923EF0", "sub_180501940", "sub_181DB6AC0", "sub_181DD5810", "sub_181DB6D10", "sub_180037B00", "sub_1839F01E0", "sub_180037810"], "callers": ["sub_181B242A0"], "xrefs": {"to": [{"addr": "0x180807376", "type": "code"}, {"addr": "0x181b242d8", "type": "code"}, {"addr": "0x181af85f9", "type": "data"}, {"addr": "0x18936ead4", "type": "data"}, {"addr": "0x18aa084b8", "type": "data"}], "from": [{"addr": "0x181b04821", "type": "code"}]}, "comments": {"0x181b04eaa": {"regular": "switch 49 cases"}, "0x181b04ec3": {"regular": "switch jump"}, "0x181b04ec5": {"repeatable": "jumptable 0000000181B04EC3 cases 3,43"}, "0x181b05168": {"repeatable": "jumptable 0000000181B04EC3 case 49"}, "0x181b05189": {"repeatable": "jumptable 0000000181B04EC3 case 1"}, "0x181b05254": {"repeatable": "jumptable 0000000181B04EC3 default case, cases 2,4-42,44-46,48"}, "0x181b05269": {"repeatable": "jumptable 0000000181B04EC3 case 47"}}, "basic_blocks": {"count": 387, "cyclomatic_complexity": 193}}, "content": [{"type": "text", "text": "{\"addr\":\"0x181b04820\",\"error\":null,\"name\":\"sub_181B04820\",\"prototype\":null,\"size\":8662,\"decompiled\":\"// Hidden C++ exception states: #wind=40\\n__int64 __fastcall sub_181B04820(__int64 a1, unsigned int a2)\\n{\\n  __int64 result; // rax\\n  _OWORD *v3; // rsi\\n  __int64 v4; // rcx\\n  __int64 v6; // rcx\\n  __int64 v7; // rax\\n  __int64 v8; // rsi\\n  __int64 v9; // r8\\n  __int128 *v10; // rdi\\n  __int64 v11; // rsi\\n  bool v12; // cf\\n  __int64 v13; // rdx\\n  __int64 v14; // rbx\\n  __int64 v15; // rax\\n  __int64 v16; // rcx\\n  unsigned __int64 v17; // rax\\n  __int64 v18; // rcx\\n  __int64 v19; // rax\\n  _OWORD *v20; // rsi\\n  __int128 v21; // kr00_16\\n  _OWORD *v22; // rcx\\n  char *v23; // rdi\\n  __int64 v24; // r12\\n  __int128 v25; // xmm0\\n  __int64 v26; // rcx\\n  __int64 v27; // rax\\n  __int64 v28; // r8\\n  __int64 v29; // r13\\n  volatile signed __int32 *v30; // rsi\\n  __int64 v31; // rdi\\n  volatile signed __int32 *v32; // rax\\n  volatile signed __int32 *v33; // rbx\\n  int i; // r14d\\n  __int128 v35; // xmm0\\n  _QWORD *v36; // r15\\n  __int64 v37; // rax\\n  __int64 v38; // rax\\n  __int64 v39; // rcx\\n  volatile signed __int32 ... [2316 chars total]\",\"decompile_truncated\":1477,\"assembly\":\"sub_181B04820 (.text @ 0x181b04820):\\n181b04820  push rbp\\n181b04821  push r15\\n181b04823  push r14\\n181b04825  push r13\\n181b04827  push r12\\n181b04829  push rsi\\n181b0482a  push rdi\\n181b0482b  push rbx\\n181b0482c  sub rsp, 458h\\n181b04833  lea rbp, [rsp+80h]\\n181b0483b  movaps [rbp+410h+var_50], xmm7\\n181b04842  movaps [rbp+410h+var_60], xmm6\\n181b04849  mov [rbp+410h+var_68], 0FFFFFFFFFFFFFFFEh\\n181b04854  cmp byte ptr [rcx+32Ch], 1\\n181b0485b  jnz loc_181B04981\\n181b04861  mov ecx, 4\\n181b04866  call sub_180068740\\n181b0486b  test eax, eax\\n181b0486d  jz loc_181B0689C\\n181b04873  lea rsi, [rbp+410h+var_220]\\n181b0487a  mov rcx, rsi\\n181b0487d  call sub_180068870\\n181b04882  cmp [rbp+410h+var_208], 10h\\n181b0488a  jb loc_181B04893\\n181b0488c  mov rsi, qword ptr [rbp+410h+var_220]\\n181b04893  lea rax, unk_1885988D3\\n181b0489a  mov [rsp+490h+var_470], rax\\n181b0489f  mov [rsp+490h+var_458], 0\\n181b048a8  mov byte ptr [rsp+490h+var_460], 0\\n181b048ad  mov dword ptr [rsp+490h+var_468], 3ADh\\n181b048b5  lea r9, unk_1... [58591 chars total]\",\"strings\":[\"sendmsg_\",\"ZYXWVUTSRQPONMLKJIHGFEDCBA9876543210123456789ABCDEFGHIJKLMNOPQRSTUVWXYZ\"],\"constants\":[],\"callees\":[\"sub_1839C7B00\",\"sub_180CE5990\",\"sub_180923EF0\",\"sub_180501940\",\"sub_181DB6AC0\",\"sub_181DD5810\",\"sub_181DB6D10\",\"sub_180037B00\",\"sub_1839F01E0\",\"sub_180037810\"],\"callers\":[\"sub_181B242A0\"],\"xrefs\":{\"to\":[{\"addr\":\"0x180807376\",\"type\":\"code\"},{\"addr\":\"0x181b242d8\",\"type\":\"code\"},{\"addr\":\"0x181af85f9\",\"type\":\"data\"},{\"addr\":\"0x18936ead4\",\"type\":\"data\"},{\"addr\":\"0x18aa084b8\",\"type\":\"data\"}],\"from\":[{\"addr\":\"0x181b04821\",\"type\":\"code\"}]},\"comments\":{\"0x181b04eaa\":{\"regular\":\"switch 49 cases\"},\"0x181b04ec3\":{\"regular\":\"switch jump\"},\"0x181b04ec5\":{\"repeatable\":\"jumptable 0000000181B04EC3 cases 3,43\"},\"0x181b05168\":{\"repeatable\":\"jumptable 0000000181B04EC3 case 49\"},\"0x181b05189\":{\"repeatable\":\"jumptable 0000000181B04EC3 case 1\"},\"0x181b05254\":{\"repeatable\":\"jumptable 0000000181B04EC3 default case, cases 2,4-42,44-46,48\"},\"0x181b05269\":{\"repeatable\":\"jumptable 0000000181B04EC3 case 47\"}},\"basic_blocks\":{\"count\":387,\"cyclomatic_complexity\":193}}"}, {"type": "text", "text": "Output truncated. Run: curl -o .ida-mcp/e4b892f4-9de6-41ca-838f-3cc7eda1b7c2.json http://127.0.0.1:13337/output/e4b892f4-9de6-41ca-838f-3cc7eda1b7c2.json"}], "isError": false, "_meta": {"ida_mcp": {"output_truncated": true, "total_chars": 64995, "output_id": "e4b892f4-9de6-41ca-838f-3cc7eda1b7c2", "download_url": "http://127.0.0.1:13337/output/e4b892f4-9de6-41ca-838f-3cc7eda1b7c2.json", "download_hint": "Output truncated. Run: curl -o .ida-mcp/e4b892f4-9de6-41ca-838f-3cc7eda1b7c2.json http://127.0.0.1:13337/output/e4b892f4-9de6-41ca-838f-3cc7eda1b7c2.json"}}}, "id": 468}